find_url/__init__.py
find_url/find.py
find_url-1.0.7.dist-info/WHEEL
find_url-1.0.7.dist-info/METADATA
find_url-1.0.7.dist-info/RECORD
