Metadata-Version: 2.1
Name: find-url
Version: 1.0.7
Summary: С помощью этой библиотеки, вы сможете парсить информацию с сайта
Author: Sergey039
Requires-Python: >=3.7,<4.0
Classifier: Programming Language :: Python :: 3
Classifier: Programming Language :: Python :: 3.7
Classifier: Programming Language :: Python :: 3.8
Classifier: Programming Language :: Python :: 3.9
Requires-Dist: requests (>=2.25.1,<3.0.0)
